LICENSE
README.md
setup.py
yollor/__init__.py
yollor/yollor.py
yollor.egg-info/PKG-INFO
yollor.egg-info/SOURCES.txt
yollor.egg-info/dependency_links.txt
yollor.egg-info/top_level.txt