Metadata-Version: 2.1
Name: yollor
Version: 2.0.0
Summary: A python library to insert colors into your code output
Author: Lucas de Moraes "Yyax13" Claro
Author-email: Yyax13@proton.me
License: MIT License
Keywords: yollor colors tags
License-File: LICENSE
